fantasy_footbot/__init__.py
fantasy_footbot/cli_functions.py
fantasy_footbot/api/__init__.py
fantasy_footbot/api/fpl_api.py
fantasy_footbot/api/player_cache.py
fantasy_footbot/building_functions/__init__.py
fantasy_footbot/building_functions/lp_max_score.py
fantasy_footbot/entities/__init__.py
fantasy_footbot/entities/player.py
fantasy_footbot/entities/team.py
fantasy_footbot/ranking_functions/__init__.py
fantasy_footbot/ranking_functions/points_per_game.py
fantasy_footbot/ranking_functions/rach_rank.py
fantasy_footbot/utility/__init__.py
fantasy_footbot/utility/build_class_for_json.py
footbot-0.1.0.dist-info/METADATA
footbot-0.1.0.dist-info/RECORD
footbot-0.1.0.dist-info/WHEEL
footbot-0.1.0.dist-info/entry_points.txt
footbot-0.1.0.dist-info/top_level.txt
