Metadata-Version: 2.1
Name: footbot
Version: 0.1.0
Summary: Picks good teams for the UK FPL Fantasy Football game
Home-page: https://github.com/rach-sharp/fantasy-footbot
Author: Rachel Sharp
Author-email: rachelsharp.dev@gmail.com
License: MIT License
Keywords: football
Platform: UNKNOWN
